{
  "id": 9,
  "title": "So What",
  "composer": "Miles Davis",
  "key": "Dm",
  "tempo": 136,
  "style": "jazz",
  "form": "AABA",
  "bars": 32,
  "progression": [
    "Dm7",
    "Dm7",
    "Dm7",
    "Dm7",
    "Dm7",
    "Dm7",
    "Dm7",
    "Dm7",
    "Dm7",
    "Dm7",
    "Dm7",
    "Dm7",
    "Dm7",
    "Dm7",
    "Dm7",
    "Dm7",
    "Ebm7",
    "Ebm7",
    "Ebm7",
    "Ebm7",
    "Ebm7",
    "Ebm7",
    "Ebm7",
    "Ebm7",
    "Dm7",
    "Dm7",
    "Dm7",
    "Dm7",
    "Dm7",
    "Dm7",
    "Dm7",
    "Dm7"
  ],
  "analysis": {
    "detected_key": "D",
    "chord_count": 32,
    "unique_chords": 2,
    "chord_diversity": 0.062,
    "avg_complexity": 35.0,
    "iivi_count": 0,
    "tritone_subs": 0,
    "tonal_range": 2,
    "extensions_used": 0,
    "extension_ratio": 0.0,
    "cadence_strength": 0.0,
    "chromatic_moves": 2,
    "unique_chord_list": [
      "Dm7",
      "Ebm7"
    ]
  },
  "simulation": {
    "wav_path": "audio/009_so_what.wav",
    "audio_duration_sec": 56.47,
    "recognition_accuracy": 0.0
  },
  "score": {
    "harmonic_richness": 44.9,
    "structural_coherence": 25.0,
    "playability": 15.0,
    "jazz_authenticity": 40,
    "overall_score": 31.7,
    "grade": "F"
  }
}