{
  "id": 36,
  "title": "Giant Steps",
  "composer": "John Coltrane",
  "key": "B",
  "tempo": 280,
  "style": "jazz",
  "form": "AABA",
  "bars": 32,
  "progression": [
    "Bmaj7",
    "D7",
    "Gmaj7",
    "Bb7",
    "Ebmaj7",
    "Am7",
    "D7",
    "Gmaj7",
    "Bb7",
    "Ebmaj7",
    "Am7",
    "D7",
    "Gmaj7",
    "Bb7",
    "Ebmaj7",
    "F#7",
    "Bmaj7",
    "Fm7",
    "Bb7",
    "Ebmaj7",
    "Am7",
    "D7",
    "Gmaj7",
    "Bb7",
    "Ebmaj7",
    "Am7",
    "D7",
    "Gmaj7",
    "Bb7",
    "Ebmaj7",
    "Bmaj7",
    "Bmaj7"
  ],
  "analysis": {
    "detected_key": "Bb",
    "chord_count": 32,
    "unique_chords": 8,
    "chord_diversity": 0.25,
    "avg_complexity": 33.1,
    "iivi_count": 7,
    "tritone_subs": 0,
    "tonal_range": 8,
    "extensions_used": 0,
    "extension_ratio": 0.0,
    "cadence_strength": 0.0,
    "chromatic_moves": 0,
    "unique_chord_list": [
      "Bmaj7",
      "D7",
      "Gmaj7",
      "Bb7",
      "Ebmaj7",
      "Am7",
      "F#7",
      "Fm7"
    ]
  },
  "simulation": {
    "wav_path": "audio/036_giant_steps.wav",
    "audio_duration_sec": 27.43,
    "recognition_accuracy": 0.125
  },
  "score": {
    "harmonic_richness": 49.0,
    "structural_coherence": 65.0,
    "playability": 46.5,
    "jazz_authenticity": 60,
    "overall_score": 56.0,
    "grade": "D"
  }
}