{
  "id": 93,
  "title": "Lover Man",
  "composer": "Jimmy Davis",
  "key": "Cm",
  "tempo": 80,
  "style": "jazz",
  "form": "AB",
  "bars": 32,
  "progression": [
    "Cm7",
    "Cm7",
    "Cm7",
    "Cm7",
    "Fm7",
    "Fm7",
    "Cm7",
    "Cm7",
    "Ab7",
    "Ab7",
    "Cm7",
    "Cm7",
    "G7",
    "G7",
    "Cm7",
    "Cm7",
    "Cm7",
    "Cm7",
    "Cm7",
    "Cm7",
    "Fm7",
    "Fm7",
    "Cm7",
    "Cm7",
    "Ab7",
    "Ab7",
    "Cm7",
    "Cm7",
    "G7",
    "G7",
    "Cm7",
    "Cm7"
  ],
  "analysis": {
    "detected_key": "C",
    "chord_count": 32,
    "unique_chords": 4,
    "chord_diversity": 0.125,
    "avg_complexity": 33.8,
    "iivi_count": 0,
    "tritone_subs": 0,
    "tonal_range": 4,
    "extensions_used": 0,
    "extension_ratio": 0.0,
    "cadence_strength": 0.0,
    "chromatic_moves": 0,
    "unique_chord_list": [
      "Cm7",
      "Fm7",
      "Ab7",
      "G7"
    ]
  },
  "simulation": {
    "wav_path": "audio/093_lover_man.wav",
    "audio_duration_sec": 96.0,
    "recognition_accuracy": 0.219
  },
  "score": {
    "harmonic_richness": 45.8,
    "structural_coherence": 23.0,
    "playability": 24.4,
    "jazz_authenticity": 40,
    "overall_score": 33.2,
    "grade": "F"
  }
}